{
  "app_details": {
    "title": "Injector Origin",
    "description": "Injector Origin is more than just an injector app. Dive into our hero guides, packed with valuable tips and tricks to master every hero's abilities and strategies. Elevate your skills and enhance your gaming experience with Injector Origin now!",
    "version": "1.7.1",
    "score": 4.4324327,
    "realInstalls": 917353,
    "released": "Jul 28, 2024",
    "lastUpdatedOn": "Oct 26, 2025"
  },
  "reviews": [
    {
      "reviewId": "745b740e-6f54-41d9-8167-2584052a530c",
      "userName": "Yuan Chavez",
      "userImage": "https://play-lh.googleusercontent.com/a-/ALV-UjUYRbcyz_cd8CfEKzypWR9a7fKMiZcnTkv6RG9vSSuKj9R9D1g",
      "content": "the app is so fun to use especially if u don't have any skinns",
      "score": 5,
      "thumbsUpCount": 0,
      "reviewCreatedVersion": "1.7.1",
      "at": "2025-10-28T22:39:10",
      "replyContent": null,
      "repliedAt": null,
      "appVersion": "1.7.1"
    },
    {
      "reviewId": "365381a2-2c8b-4b74-b665-880579921167",
      "userName": "Uyammi Lester",
      "userImage": "https://play-lh.googleusercontent.com/a/ACg8ocL2x6_VSTzlKJBplF_mRhhcq8Pd8MkGfoDcRa56f35RWF6b1g=mo",
      "content": "thank God for my best friend",
      "score": 5,
      "thumbsUpCount": 0,
      "reviewCreatedVersion": "1.7.1",
      "at": "2025-10-28T15:07:56",
      "replyContent": null,
      "repliedAt": null,
      "appVersion": "1.7.1"
    },
    {
      "reviewId": "05cdbd46-a243-4aed-a958-49ec8a532aa0",
      "userName": "Noan Madejabaluyot",
      "userImage": "https://play-lh.googleusercontent.com/a/ACg8ocILICEjtBZiNXOJSVCbciox00WcOLwGk0dXIed24qzBz5FhWg=mo",
      "content": "ilove it",
      "score": 5,
      "thumbsUpCount": 0,
      "reviewCreatedVersion": "1.7.1",
      "at": "2025-10-28T10:40:13",
      "replyContent": null,
      "repliedAt": null,
      "appVersion": "1.7.1"
    },
    {
      "reviewId": "3d4dd9fb-375e-4d3d-a6e9-5746b01d5953",
      "userName": "bernard Mendoza",
      "userImage": "https://play-lh.googleusercontent.com/a/ACg8ocKcPp1rJFarCvODt4nTOpBK8Ahwf_Gsb1KxICGZU6mp1mKJrQ=mo",
      "content": "yesl",
      "score": 2,
      "thumbsUpCount": 0,
      "reviewCreatedVersion": "1.7.1",
      "at": "2025-10-28T05:38:10",
      "replyContent": null,
      "repliedAt": null,
      "appVersion": "1.7.1"
    },
    {
      "reviewId": "b921d8f5-0f58-4f0f-911c-67b53bd5a798",
      "userName": "Warrin Capuno",
      "userImage": "https://play-lh.googleusercontent.com/a-/ALV-UjXkViSTO6oU8lRL1M-o_9_x9Ey1EglXUTI_knT6Dog_hdvkmdQ",
      "content": "nice app",
      "score": 3,
      "thumbsUpCount": 0,
      "reviewCreatedVersion": "1.7.1",
      "at": "2025-10-27T13:41:25",
      "replyContent": null,
      "repliedAt": null,
      "appVersion": "1.7.1"
    }
  ],
  "generated_at": "2025-10-30T02:02:47.032758"
}