{
  "app_details": {
    "title": "Injector Origin",
    "description": "Injector Origin is more than just an injector app. Dive into our hero guides, packed with valuable tips and tricks to master every hero's abilities and strategies. Elevate your skills and enhance your gaming experience with Injector Origin now!",
    "version": "1.6.4",
    "score": 4.6060605,
    "realInstalls": 735848,
    "released": "Jul 28, 2024",
    "lastUpdatedOn": "Jul 9, 2025"
  },
  "reviews": [
    {
      "reviewId": "875b7a91-04c1-4e59-a467-f5be304226fb",
      "userName": "John poul Longcob",
      "userImage": "https://play-lh.googleusercontent.com/a/ACg8ocITuw4DawdJqXmDPTtEr7ZZIt2jMF56inQueVV_YE18T8dQQA=mo",
      "content": "\ud835\udc4a\ud835\udc59\ud835\udc4e \ud835\udc4e\ud835\udc58\ud835\udc5c\ud835\udc5b\ud835\udc54 \ud835\udc60\ud835\udc58\ud835\udc56\ud835\udc5b \ud835\udc58\ud835\udc4e\ud835\udc66\ud835\udc4e \ud835\udc5a\ud835\udc4e\ud835\udc54 \ud835\udc56\ud835\udc5b\ud835\udc57\ud835\udc52\ud835\udc50\ud835\udc61 \ud835\udc5b\ud835\udc59\ud835\udc5b\ud835\udc54 \ud835\udc4e\ud835\udc58\ud835\udc5c",
      "score": 5,
      "thumbsUpCount": 0,
      "reviewCreatedVersion": null,
      "at": "2025-07-27T23:13:51",
      "replyContent": null,
      "repliedAt": null,
      "appVersion": null
    },
    {
      "reviewId": "e18be580-a133-446b-81af-80084dc694f6",
      "userName": "Faroogh Haftjoosh (DINCO)",
      "userImage": "https://play-lh.googleusercontent.com/a-/ALV-UjUk08lidcUlQXBpMqAeryg2EQwjcsviO3QBLsPs7SIdmrUkts8T",
      "content": "The best of the bestttt",
      "score": 5,
      "thumbsUpCount": 0,
      "reviewCreatedVersion": null,
      "at": "2025-07-27T21:35:32",
      "replyContent": null,
      "repliedAt": null,
      "appVersion": null
    },
    {
      "reviewId": "45c47323-423d-40f2-8088-f947b3529e62",
      "userName": "Narutouzumaki Uzumaki",
      "userImage": "https://play-lh.googleusercontent.com/a/ACg8ocLAiwEwvYQ9mfQFPJ3wPSQ4UtZYnx-a2g2wRTHCKHpRvC6OLw=mo",
      "content": "Pls add New skin and coming soon skin mlbb plisssss i like u app",
      "score": 5,
      "thumbsUpCount": 0,
      "reviewCreatedVersion": null,
      "at": "2025-07-27T07:59:51",
      "replyContent": null,
      "repliedAt": null,
      "appVersion": null
    },
    {
      "reviewId": "e580a779-d257-4c48-8d9f-06ca33fa566b",
      "userName": "Prince Denielle Albiola",
      "userImage": "https://play-lh.googleusercontent.com/a/ACg8ocIBsV7HzYO6cHdB2jP_8opdjJtH3B3D4tJyXRX7-87pXmotZw=mo",
      "content": "I recommend this app to everyone I've been using this for years yet it's the best injector compared to vinns tools and zen hub",
      "score": 5,
      "thumbsUpCount": 0,
      "reviewCreatedVersion": "1.6.4",
      "at": "2025-07-27T05:57:07",
      "replyContent": null,
      "repliedAt": null,
      "appVersion": "1.6.4"
    },
    {
      "reviewId": "ce521e57-400a-44a4-96e6-9cfcbe34b025",
      "userName": "Mark Bajenting",
      "userImage": "https://play-lh.googleusercontent.com/a/ACg8ocIFpfF0BZWzYBhKCxlT16zH9IFlLq-9issxsKzElc-Xs64lDA=mo",
      "content": "I'm so happy",
      "score": 5,
      "thumbsUpCount": 0,
      "reviewCreatedVersion": "1.6.4",
      "at": "2025-07-27T02:08:58",
      "replyContent": null,
      "repliedAt": null,
      "appVersion": "1.6.4"
    }
  ],
  "generated_at": "2025-07-29T02:32:12.657079"
}