{
  "app_details": {
    "title": "Injector Origin",
    "description": "Injector Origin is more than just an injector app. Dive into our hero guides, packed with valuable tips and tricks to master every hero's abilities and strategies. Elevate your skills and enhance your gaming experience with Injector Origin now!",
    "version": "1.6.5",
    "score": 4.6060605,
    "realInstalls": 776324,
    "released": "Jul 28, 2024",
    "lastUpdatedOn": "Aug 19, 2025"
  },
  "reviews": [
    {
      "reviewId": "35e67863-a65e-4820-abce-c93f9a35821e",
      "userName": "Brench Bayatan",
      "userImage": "https://play-lh.googleusercontent.com/a/ACg8ocKkbbjxgR_b-UaNEg9HaIZQtMaDleW37QBGeklIfZ48EVsjZQ=mo",
      "content": "keren skinmlbb",
      "score": 4,
      "thumbsUpCount": 0,
      "reviewCreatedVersion": null,
      "at": "2025-08-19T01:42:08",
      "replyContent": null,
      "repliedAt": null,
      "appVersion": null
    },
    {
      "reviewId": "25efdb7e-0e96-4fc3-a8f6-e38d1912126e",
      "userName": "Lj Hernal",
      "userImage": "https://play-lh.googleusercontent.com/a-/ALV-UjXJxF_objsD71KYEtjFaChhbYqmUi6pOo4NZ_qY5rmJNGAevX-E",
      "content": "awsome",
      "score": 5,
      "thumbsUpCount": 0,
      "reviewCreatedVersion": "1.6.4",
      "at": "2025-08-18T15:46:14",
      "replyContent": null,
      "repliedAt": null,
      "appVersion": "1.6.4"
    },
    {
      "reviewId": "03fe89cb-3a20-41d9-ac54-3c634c067d09",
      "userName": "John Mark Grabador",
      "userImage": "https://play-lh.googleusercontent.com/a/ACg8ocLSs55pUXitJQjxf7Fsn5zYltdcbg1GCk1Np7OexK5o_Hywcg=mo",
      "content": "beautiful app",
      "score": 5,
      "thumbsUpCount": 0,
      "reviewCreatedVersion": "1.6.4",
      "at": "2025-08-18T14:29:58",
      "replyContent": null,
      "repliedAt": null,
      "appVersion": "1.6.4"
    },
    {
      "reviewId": "6a5b4b7c-3389-4ac7-8a52-53341145f5f4",
      "userName": "Darren",
      "userImage": "https://play-lh.googleusercontent.com/a/ACg8ocIkNEZ96OAFiPs4m7kP-q55kL9ZVjRtqysNfWcCgU3oeccH0Q=mo",
      "content": "Keren banget gak pake ling atau com",
      "score": 5,
      "thumbsUpCount": 0,
      "reviewCreatedVersion": "1.6.4",
      "at": "2025-08-18T13:46:06",
      "replyContent": null,
      "repliedAt": null,
      "appVersion": "1.6.4"
    },
    {
      "reviewId": "4ea4454f-d164-40ce-bcd4-28ce36f31ebf",
      "userName": "Jove Desalia",
      "userImage": "https://play-lh.googleusercontent.com/a/ACg8ocKiMaS6ROEQXSq1uuzzJM4W45-GxIrfdA_YDfB810D8bOjYZw=mo",
      "content": "no upgrade skin natalia\ud83d\udc4e\ud83c\udffb",
      "score": 2,
      "thumbsUpCount": 0,
      "reviewCreatedVersion": "1.6.4",
      "at": "2025-08-18T12:10:37",
      "replyContent": null,
      "repliedAt": null,
      "appVersion": "1.6.4"
    }
  ],
  "generated_at": "2025-08-20T01:59:41.950511"
}