{
  "app_details": {
    "title": "Injector Origin",
    "description": "Injector Origin is more than just an injector app. Dive into our hero guides, packed with valuable tips and tricks to master every hero's abilities and strategies. Elevate your skills and enhance your gaming experience with Injector Origin now!",
    "version": "1.6.1",
    "score": 4.642857,
    "realInstalls": 573652,
    "released": "Jul 28, 2024",
    "lastUpdatedOn": "Feb 17, 2025"
  },
  "reviews": [
    {
      "reviewId": "72d60c57-e516-4d31-a952-bb49a014a378",
      "userName": "John Mark",
      "userImage": "https://play-lh.googleusercontent.com/a/ACg8ocIKCEztf1gscy8bA7VUm6Ss0b7xdguR04QIekpgBQ0Os3pozg=mo",
      "content": "not really interested",
      "score": 4,
      "thumbsUpCount": 0,
      "reviewCreatedVersion": null,
      "at": "2025-05-17T17:18:50",
      "replyContent": null,
      "repliedAt": null,
      "appVersion": null
    },
    {
      "reviewId": "b6d8308f-9d45-4c3b-8cf4-26a714461c80",
      "userName": "Phillip roque Sagun",
      "userImage": "https://play-lh.googleusercontent.com/a/ACg8ocLyJ_Js-StX_44t9kLYpx0R5JJJizTrobpn7BpYj9H9C2k4Zw=mo",
      "content": "ok",
      "score": 3,
      "thumbsUpCount": 0,
      "reviewCreatedVersion": "1.6.1",
      "at": "2025-05-17T14:00:26",
      "replyContent": null,
      "repliedAt": null,
      "appVersion": "1.6.1"
    },
    {
      "reviewId": "c176a343-f813-4a31-8c64-ff6a0b2c24dc",
      "userName": "kierxyrusnollas",
      "userImage": "https://play-lh.googleusercontent.com/a-/ALV-UjXFsV-I4Kx9aCdoshjBbj2nuEWpHPbw9M2gsh_xoSwvHRnhwXLz",
      "content": "I love it!",
      "score": 5,
      "thumbsUpCount": 0,
      "reviewCreatedVersion": "1.6.1",
      "at": "2025-05-17T10:35:26",
      "replyContent": null,
      "repliedAt": null,
      "appVersion": "1.6.1"
    },
    {
      "reviewId": "72cb5e55-99bf-4c38-9692-65d4f75c55c6",
      "userName": "Angielo Angeles",
      "userImage": "https://play-lh.googleusercontent.com/a-/ALV-UjWzoVap7rZyavzt5GAQl79IiuoE-rsJLH5Qd83vvuqEJdE0TLym",
      "content": "need updated for marksmans skins best skin in this injector is legend skin granger and mosvoc abyss",
      "score": 5,
      "thumbsUpCount": 0,
      "reviewCreatedVersion": "1.6.1",
      "at": "2025-05-17T07:25:46",
      "replyContent": null,
      "repliedAt": null,
      "appVersion": "1.6.1"
    },
    {
      "reviewId": "108cc478-e190-4d54-bd13-3ab8caa505f0",
      "userName": "Jorge playz Baco",
      "userImage": "https://play-lh.googleusercontent.com/a/ACg8ocKUtG1svRoo9YL45LycwkEMS9FF0DW0blJFRajWN-ipMZE5AA=mo",
      "content": "cool",
      "score": 5,
      "thumbsUpCount": 0,
      "reviewCreatedVersion": "1.6.1",
      "at": "2025-05-17T04:39:36",
      "replyContent": null,
      "repliedAt": null,
      "appVersion": "1.6.1"
    }
  ],
  "generated_at": "2025-05-19T02:07:31.930293"
}