{
  "app_details": {
    "title": "Injector Origin",
    "description": "Injector Origin is more than just an injector app. Dive into our hero guides, packed with valuable tips and tricks to master every hero's abilities and strategies. Elevate your skills and enhance your gaming experience with Injector Origin now!",
    "version": "1.1.0 fix1",
    "score": 0,
    "realInstalls": 38971,
    "released": "Jul 28, 2024",
    "lastUpdatedOn": "Sep 12, 2024"
  },
  "reviews": [
    {
      "reviewId": "7174e94c-9fe1-40ef-ba22-4e97fdc30f4b",
      "userName": "Mijaylla Khendra Besa",
      "userImage": "https://play-lh.googleusercontent.com/a-/ALV-UjUBMb8QTLeN6W-tcWziZ6ZatEWkEPBx2mdKhlciYyf4O8jVcw0v",
      "content": "I hoped this will not ban me\ud83d\ude04",
      "score": 5,
      "thumbsUpCount": 0,
      "reviewCreatedVersion": null,
      "at": "2024-09-22T13:34:28",
      "replyContent": "We understand your concern! We\u2019re committed to ensuring the best experience while prioritizing safety. Always use the app responsibly and avoid suspicious activity in-game. If you have any questions or need assistance, feel free to reach out. Stay safe and happy gaming! \ud83c\udfae",
      "repliedAt": "2024-09-23T06:01:47",
      "appVersion": null
    },
    {
      "reviewId": "6c346eeb-71f9-40be-a33e-e3abf77baea7",
      "userName": "Reymark",
      "userImage": "https://play-lh.googleusercontent.com/a/ACg8ocKihTnjUydWgO3DGLzD8QPH2Lpyuo0VBVcEnerFxjZO_XKT6w=mo",
      "content": "Salamat sa skin",
      "score": 5,
      "thumbsUpCount": 0,
      "reviewCreatedVersion": null,
      "at": "2024-09-22T10:41:23",
      "replyContent": "You're welcome! Glad you're enjoying the app. If you need anything else or have any feedback, feel free to let us know. Happy gaming!",
      "repliedAt": "2024-09-23T06:00:56",
      "appVersion": null
    },
    {
      "reviewId": "91fe8861-88ce-4f71-9230-3ec55cab2ea1",
      "userName": "Kenth Dadivas",
      "userImage": "https://play-lh.googleusercontent.com/a/ACg8ocKoghi-SVQSyYYeST-NUMts07v9DIoVA-VOITJcVoGF31wwMQ=mo",
      "content": "okay",
      "score": 5,
      "thumbsUpCount": 0,
      "reviewCreatedVersion": "1.1.0 fix1",
      "at": "2024-09-22T07:53:57",
      "replyContent": "Thank you! If you have any questions or feedback, feel free to reach out anytime. We're here to help!\n\n",
      "repliedAt": "2024-09-23T05:59:53",
      "appVersion": "1.1.0 fix1"
    },
    {
      "reviewId": "33f1f95a-bb59-4ed0-9b4f-7d4bbfa872b6",
      "userName": "Nyanbeni Kikon",
      "userImage": "https://play-lh.googleusercontent.com/a-/ALV-UjXecn-O_3JOsVaW--w3JSQ-1-TeNBhyMNTPMRLAxAMcexnv130o",
      "content": "very good",
      "score": 3,
      "thumbsUpCount": 0,
      "reviewCreatedVersion": "1.1.0 fix1",
      "at": "2024-09-22T05:22:26",
      "replyContent": "Thank you so much! We're happy to hear that you're enjoying the app. If you have any suggestions or need assistance, feel free to let us know. We\u2019re always here to help and improve your experience!",
      "repliedAt": "2024-09-23T05:59:30",
      "appVersion": "1.1.0 fix1"
    },
    {
      "reviewId": "01ec083f-e0dd-4118-9fe5-436fbaf40c49",
      "userName": "Bren scyte\u30b7",
      "userImage": "https://play-lh.googleusercontent.com/a-/ALV-UjX-Pm4r7FiIFhbYRVR6JNyrw74-mN8AeH_oV57_KXA3AKQCWXU",
      "content": "okay mmn sya",
      "score": 5,
      "thumbsUpCount": 0,
      "reviewCreatedVersion": "1.1.0 fix1",
      "at": "2024-09-22T03:47:43",
      "replyContent": "Thanks for your feedback! If there\u2019s anything we can improve, feel free to share. We're here to help!",
      "repliedAt": "2024-09-23T05:58:58",
      "appVersion": "1.1.0 fix1"
    }
  ],
  "generated_at": "2024-09-24T01:19:11.229633"
}